simplecurry
