Metadata-Version: 1.0
Name: simplecurry
Version: 1.12
Summary: Curried decorator
Home-page: https://github.com/grimborg/simplecurry
Author: Òscar Vilaplana
Author-email: dev@oscarvilaplana.cat
License: http://www.gnu.org/licenses/gpl-2.0.html
Platform: UNKNOWN
